fastapi_factory_utilities/__main__.py
fastapi_factory_utilities/core/__init__.py
fastapi_factory_utilities/core/api/__init__.py
fastapi_factory_utilities/core/api/tags.py
fastapi_factory_utilities/core/api/v1/sys/__init__.py
fastapi_factory_utilities/core/api/v1/sys/health.py
fastapi_factory_utilities/core/api/v1/sys/readiness.py
fastapi_factory_utilities/core/app/__init__.py
fastapi_factory_utilities/core/app/application.py
fastapi_factory_utilities/core/app/builder.py
fastapi_factory_utilities/core/app/config.py
fastapi_factory_utilities/core/app/depends.py
fastapi_factory_utilities/core/app/enums.py
fastapi_factory_utilities/core/app/exceptions.py
fastapi_factory_utilities/core/app/fastapi_builder.py
fastapi_factory_utilities/core/exceptions.py
fastapi_factory_utilities/core/plugins/__init__.py
fastapi_factory_utilities/core/plugins/abstracts.py
fastapi_factory_utilities/core/plugins/aiohttp/__init__.py
fastapi_factory_utilities/core/plugins/aiohttp/builder.py
fastapi_factory_utilities/core/plugins/aiohttp/configs.py
fastapi_factory_utilities/core/plugins/aiohttp/constants.py
fastapi_factory_utilities/core/plugins/aiohttp/depends.py
fastapi_factory_utilities/core/plugins/aiohttp/exceptions.py
fastapi_factory_utilities/core/plugins/aiohttp/factories.py
fastapi_factory_utilities/core/plugins/aiohttp/mockers.py
fastapi_factory_utilities/core/plugins/aiohttp/plugins.py
fastapi_factory_utilities/core/plugins/aiohttp/resources.py
fastapi_factory_utilities/core/plugins/aiopika/__init__.py
fastapi_factory_utilities/core/plugins/aiopika/abstract.py
fastapi_factory_utilities/core/plugins/aiopika/depends.py
fastapi_factory_utilities/core/plugins/aiopika/exceptions.py
fastapi_factory_utilities/core/plugins/aiopika/exchange.py
fastapi_factory_utilities/core/plugins/aiopika/listener/__init__.py
fastapi_factory_utilities/core/plugins/aiopika/listener/abstract.py
fastapi_factory_utilities/core/plugins/aiopika/message.py
fastapi_factory_utilities/core/plugins/aiopika/plugins.py
fastapi_factory_utilities-0.16.0.dist-info/METADATA
fastapi_factory_utilities-0.16.0.dist-info/WHEEL
fastapi_factory_utilities-0.16.0.dist-info/entry_points.txt
fastapi_factory_utilities-0.16.0.dist-info/licenses/LICENSE
fastapi_factory_utilities-0.16.0.dist-info/RECORD
