Metadata-Version: 2.4
Name: fastapi_factory_utilities
Version: 0.16.0
Summary: Consolidate libraries and utilities to create microservices in Python with FastAPI, Beanie, Taskiq, AioPika and OpenTelemetry.
License: MIT
License-File: LICENSE
Keywords: python,fastapi,beanie,taskiq,opentelemetry,microservices
Author: miragecentury
Author-email: victorien.vanroye@gmail.com
Maintainer: miragecentury
Maintainer-email: victorien.vanroye@gmail.com
Requires-Python: >=3.12,<4.0
Classifier: Development Status :: 3 - Alpha
Classifier: Intended Audience :: Developers
Classifier: License :: OSI Approved :: MIT License
Classifier: Operating System :: OS Independent
Classifier: Programming Language :: Python :: 3
Classifier: Programming Language :: Python :: 3.12
Classifier: Programming Language :: Python :: 3.13
Classifier: Programming Language :: Python :: 3.14
Classifier: Topic :: Software Development :: Libraries
Classifier: Topic :: Software Development :: Libraries :: Application Frameworks
Classifier: Topic :: Software Development :: Libraries :: Python Modules
Requires-Dist: aio-pika (>=9.5.7,<10.0.0)
Requires-Dist: aiohttp[speedups] (>=3.12.13,<4.0.0)
Requires-Dist: beanie (>=2.0.0,<3.0.0)
Requires-Dist: certifi (>=2025.11.12,<2026.0.0)
Requires-Dist: fastapi (>=0.115.13,<1)
Requires-Dist: opentelemetry-exporter-otlp-proto-grpc (>=1.26.0,<2.0.0)
Requires-Dist: opentelemetry-exporter-otlp-proto-http (>=1.26.0,<2.0.0)
Requires-Dist: opentelemetry-instrumentation-aio-pika (>=0.60b0,<0.61)
Requires-Dist: opentelemetry-instrumentation-aiohttp-client (>=0,<1)
Requires-Dist: opentelemetry-instrumentation-fastapi (>=0,<1)
Requires-Dist: opentelemetry-instrumentation-pymongo (>=0,<1)
Requires-Dist: opentelemetry-propagator-b3 (>=1.26.0,<2.0.0)
Requires-Dist: opentelemetry-sdk (>=1.26.0,<2.0.0)
Requires-Dist: pyaml (>=25.1.0,<26.0.0)
Requires-Dist: pydantic (>=2.8.2,<3.0.0)
Requires-Dist: pyjwt (>=2.10.1,<3.0.0)
Requires-Dist: pymongo (>=4.9.2,<4.16.0)
Requires-Dist: reactivex (>=4.0.4,<5.0.0)
Requires-Dist: structlog (>=24.1,<26.0)
Requires-Dist: taskiq-dependencies (>=1.5.8,<2.0.0)
Requires-Dist: taskiq-fastapi (>=0.3.5,<0.4.0)
Requires-Dist: taskiq-redis (>=1.0.9,<2.0.0)
Requires-Dist: typer (>=0,<1)
Requires-Dist: uvicorn (>=0.34.3,<1)
Project-URL: Homepage, https://github.com/DeerHide/fastapi_factory_utilities
Project-URL: Repository, https://github.com/DeerHide/fastapi_factory_utilities
